package/__init__.py
package/main.py
spouk_firebird_utils-0.0.2.dist-info/LICENSE
spouk_firebird_utils-0.0.2.dist-info/METADATA
spouk_firebird_utils-0.0.2.dist-info/WHEEL
spouk_firebird_utils-0.0.2.dist-info/top_level.txt
spouk_firebird_utils-0.0.2.dist-info/RECORD
