Metadata-Version: 2.1
Name: spouk-firebird-utils
Version: 0.0.2
Summary: utils for working with firebird databases
Home-page: https://gitlab.com/Spouk
Author: spouk
Author-email: cyberspouk@gmail.com
License: MIT
Classifier: Programming Language :: Python :: 3.11
Classifier: License :: OSI Approved :: MIT License
Classifier: Operating System :: OS Independent
Requires-Python: >=3.7
License-File: LICENSE
Requires-Dist: fdb (>=2.0.2)
